README.md
setup.py
pulumi_buildkite/__init__.py
pulumi_buildkite/_inputs.py
pulumi_buildkite/_utilities.py
pulumi_buildkite/agent_token.py
pulumi_buildkite/get_meta.py
pulumi_buildkite/get_pipeline.py
pulumi_buildkite/get_team.py
pulumi_buildkite/outputs.py
pulumi_buildkite/pipeline.py
pulumi_buildkite/pipeline_schedule.py
pulumi_buildkite/provider.py
pulumi_buildkite/pulumi-plugin.json
pulumi_buildkite/py.typed
pulumi_buildkite/team.py
pulumi_buildkite/team_member.py
pulumi_buildkite.egg-info/PKG-INFO
pulumi_buildkite.egg-info/SOURCES.txt
pulumi_buildkite.egg-info/dependency_links.txt
pulumi_buildkite.egg-info/not-zip-safe
pulumi_buildkite.egg-info/requires.txt
pulumi_buildkite.egg-info/top_level.txt
pulumi_buildkite/config/__init__.py
pulumi_buildkite/config/vars.py