Metadata-Version: 2.1
Name: pulumi-buildkite
Version: 0.2.1
Summary: A Pulumi package for creating and managing Buildkite CI/CD platform resources.
Home-page: https://pulumi.io
License: Apache-2.0
Project-URL: Repository, https://github.com/grapl-security/pulumi-buildkite
Keywords: pulumi buildkite category/infrastructure
Platform: UNKNOWN
